{"expires":1726218391038,"value":{"code":200,"headers":{"etag":"W/\"zlL7DV6Q9t\"","last-modified":"Fri, 06 Sep 2024 09:06:31 GMT","cache-control":"max-age=604800"},"body":{"prefix":"majesticons","lastModified":1722794692,"aliases":{},"width":24,"height":24,"icons":{"user-box-line":{"body":"<g fill=\"none\" stroke=\"currentColor\" stroke-linecap=\"round\" stroke-linejoin=\"round\" stroke-width=\"2\"><circle cx=\"12\" cy=\"10\" r=\"3\"/><path d=\"M17 17c0-2.21-2.239-4-5-4s-5 1.79-5 4\"/><rect width=\"18\" height=\"18\" x=\"3\" y=\"3\" rx=\"3\"/></g>"}}}},"mtime":1725613591325,"integrity":"mJupSPVW3X"}