{"expires":1726634585348,"value":{"code":200,"headers":{"etag":"W/\"d4lgCGujIJ\"","last-modified":"Wed, 11 Sep 2024 04:43:05 GMT","cache-control":"max-age=604800"},"body":{"prefix":"heroicons","icons":{"chevron-down-20-solid":{"body":"<path fill=\"currentColor\" fill-rule=\"evenodd\" d=\"M5.22 8.22a.75.75 0 0 1 1.06 0L10 11.94l3.72-3.72a.75.75 0 1 1 1.06 1.06l-4.25 4.25a.75.75 0 0 1-1.06 0L5.22 9.28a.75.75 0 0 1 0-1.06\" clip-rule=\"evenodd\"/>","width":20,"height":20},"magnifying-glass-20-solid":{"body":"<path fill=\"currentColor\" fill-rule=\"evenodd\" d=\"M9 3.5a5.5 5.5 0 1 0 0 11a5.5 5.5 0 0 0 0-11M2 9a7 7 0 1 1 12.452 4.391l3.328 3.329a.75.75 0 1 1-1.06 1.06l-3.329-3.328A7 7 0 0 1 2 9\" clip-rule=\"evenodd\"/>","width":20,"height":20}},"lastModified":1721921294,"width":24,"height":24}},"mtime":1726029785349,"integrity":"mJupSPVW3X"}